<?xml version="1.0" encoding="UTF-8"?>
<record_update sys_domain="global" table="pa_cubes">
    <pa_cubes action="INSERT_OR_UPDATE">
        <conditions table="x_14806_marketing_attendee">registration_dateON2017-04-12@javascript:gs.dateGenerate('2017-04-12','start')@javascript:gs.dateGenerate('2017-04-12','end')<item endquery="false" field="registration_date" goto="false" newquery="false" operator="ON" or="false" value="2017-04-12@javascript:gs.dateGenerate('2017-04-12','start')@javascript:gs.dateGenerate('2017-04-12','end')"/>
        </conditions>
        <description/>
        <facts_table>x_14806_marketing_attendee</facts_table>
        <facts_table_pk/>
        <facts_table_pktable/>
        <facts_table_pkview/>
        <frequency>10</frequency>
        <name>Registration</name>
        <report_source/>
        <report_source_updated_at/>
        <sys_class_name>pa_cubes</sys_class_name>
        <sys_created_by>admin</sys_created_by>
        <sys_created_on>2017-04-12 20:13:58</sys_created_on>
        <sys_customer_update>true</sys_customer_update>
        <sys_domain>global</sys_domain>
        <sys_domain_path>/</sys_domain_path>
        <sys_id>e4ea3092db023200a1acd8c0cf9619c5</sys_id>
        <sys_mod_count>0</sys_mod_count>
        <sys_name>Registration</sys_name>
        <sys_overrides/>
        <sys_package display_value="Marketing Events Application" source="x_14806_marketing">3b7ed2ef0f85020078648fcce1050e5a</sys_package>
        <sys_policy/>
        <sys_replace_on_upgrade>false</sys_replace_on_upgrade>
        <sys_scope display_value="Marketing Events Application">3b7ed2ef0f85020078648fcce1050e5a</sys_scope>
        <sys_update_name>pa_cubes_e4ea3092db023200a1acd8c0cf9619c5</sys_update_name>
        <sys_updated_by>admin</sys_updated_by>
        <sys_updated_on>2017-04-12 20:13:58</sys_updated_on>
    </pa_cubes>
    <sys_translated_text action="delete_multiple" query="documentkey=e4ea3092db023200a1acd8c0cf9619c5"/>
</record_update>
